yta_file_downloader/__init__.py
yta_file_downloader/downloader/__init__.py
yta_file_downloader/downloader/audio.py
yta_file_downloader/downloader/gif.py
yta_file_downloader/downloader/image.py
yta_file_downloader/downloader/video.py
yta_file_downloader/downloader/web/__init__.py
yta_file_downloader/downloader/web/facebook/__init__.py
yta_file_downloader/downloader/web/facebook/dataclasses.py
yta_file_downloader/downloader/web/facebook/downloader.py
yta_file_downloader/downloader/web/facebook/url_parser.py
yta_file_downloader/downloader/web/instagram/__init__.py
yta_file_downloader/downloader/web/instagram/dataclasses.py
yta_file_downloader/downloader/web/instagram/downloader.py
yta_file_downloader/downloader/web/instagram/url_parser.py
yta_file_downloader/downloader/web/tiktok/__init__.py
yta_file_downloader/downloader/web/tiktok/dataclasses.py
yta_file_downloader/downloader/web/tiktok/downloader.py
yta_file_downloader/downloader/web/tiktok/url_parser.py
yta_file_downloader/utils.py
yta_file_downloader-0.0.10.dist-info/licenses/LICENSE
yta_file_downloader-0.0.10.dist-info/METADATA
yta_file_downloader-0.0.10.dist-info/WHEEL
yta_file_downloader-0.0.10.dist-info/RECORD
